wservice_client/__init__.py
wservice_client/wservice_client.py
wservice_client-1.1.1.dist-info/METADATA
wservice_client-1.1.1.dist-info/WHEEL
wservice_client-1.1.1.dist-info/top_level.txt
wservice_client-1.1.1.dist-info/RECORD
