Metadata-Version: 2.1
Name: wservice-client
Version: 1.1.1
Summary: A Python client for web service communication
Home-page: https://github.com/mnedev-cell/wservice_client.git
Author: DEVMNE
Author-email: mne@yaposarl.ma
Classifier: Programming Language :: Python :: 3
Classifier: License :: OSI Approved :: MIT License
Requires-Python: >=3.6
Requires-Dist: requests
